resource_lock/__init__.py
resource_lock/resource_lock.py
resource_lock-0.6.0.dist-info/METADATA
resource_lock-0.6.0.dist-info/WHEEL
resource_lock-0.6.0.dist-info/top_level.txt
resource_lock-0.6.0.dist-info/RECORD
